Metadata-Version: 2.1
Name: bincrypt
Version: 0.2
Summary: A simple way to convert ASCII to binary and the other way
Author: Matel Matel
